lib_log_rich/__init__.py
lib_log_rich/__init__conf__.py
lib_log_rich/__main__.py
lib_log_rich/cli.py
lib_log_rich/cli_stresstest.py
lib_log_rich/config.py
lib_log_rich/defaultconfig.toml
lib_log_rich/demo.py
lib_log_rich/lib_log_rich.py
lib_log_rich/py.typed
lib_log_rich/adapters/__init__.py
lib_log_rich/adapters/_formatting.py
lib_log_rich/adapters/_json_coerce.py
lib_log_rich/adapters/_queue_worker.py
lib_log_rich/adapters/_schemas.py
lib_log_rich/adapters/_text_utils.py
lib_log_rich/adapters/dump.py
lib_log_rich/adapters/graylog.py
lib_log_rich/adapters/queue.py
lib_log_rich/adapters/rate_limiter.py
lib_log_rich/adapters/scrubber.py
lib_log_rich/adapters/console/__init__.py
lib_log_rich/adapters/console/queue_console.py
lib_log_rich/adapters/console/rich_console.py
lib_log_rich/adapters/structured/__init__.py
lib_log_rich/adapters/structured/journald.py
lib_log_rich/adapters/structured/windows_eventlog.py
lib_log_rich/application/__init__.py
lib_log_rich/application/ports/__init__.py
lib_log_rich/application/ports/console.py
lib_log_rich/application/ports/dump.py
lib_log_rich/application/ports/graylog.py
lib_log_rich/application/ports/identity.py
lib_log_rich/application/ports/queue.py
lib_log_rich/application/ports/rate_limiter.py
lib_log_rich/application/ports/scrubber.py
lib_log_rich/application/ports/structures.py
lib_log_rich/application/ports/time.py
lib_log_rich/application/use_cases/__init__.py
lib_log_rich/application/use_cases/_fan_out.py
lib_log_rich/application/use_cases/_payload_sanitizer.py
lib_log_rich/application/use_cases/_pipeline.py
lib_log_rich/application/use_cases/_queue_dispatch.py
lib_log_rich/application/use_cases/_types.py
lib_log_rich/application/use_cases/dump.py
lib_log_rich/application/use_cases/process_event.py
lib_log_rich/application/use_cases/shutdown.py
lib_log_rich/defaultconfig.d/90-logging.toml
lib_log_rich/domain/__init__.py
lib_log_rich/domain/analytics.py
lib_log_rich/domain/context.py
lib_log_rich/domain/dump.py
lib_log_rich-6.3.1.dist-info/METADATA
lib_log_rich-6.3.1.dist-info/WHEEL
lib_log_rich-6.3.1.dist-info/entry_points.txt
lib_log_rich-6.3.1.dist-info/licenses/LICENSE
lib_log_rich-6.3.1.dist-info/RECORD
